rs1101/__init__.py
rs1101/cli.py
rs1101/random_format.py
rs1101/random_int.py
rs1101/random_string.py
rs1101-0.3.8.dist-info/METADATA
rs1101-0.3.8.dist-info/WHEEL
rs1101-0.3.8.dist-info/entry_points.txt
rs1101-0.3.8.dist-info/top_level.txt
rs1101-0.3.8.dist-info/RECORD
